README.md
setup.py
PrefectDecorator/__init__.py
PrefectDecorator/save_to_file.py
PrefectDecorator.egg-info/PKG-INFO
PrefectDecorator.egg-info/SOURCES.txt
PrefectDecorator.egg-info/dependency_links.txt
PrefectDecorator.egg-info/top_level.txt